azureml/__init__.py
azureml/contrib/__init__.py
azureml/contrib/automl/__init__.py
azureml/contrib/automl/pipeline/__init__.py
azureml/contrib/automl/pipeline/steps/__init__.py
azureml/contrib/automl/pipeline/steps/_hts_pipeline_builder.py
azureml/contrib/automl/pipeline/steps/automl_pipeline_builder.py
azureml/contrib/automl/pipeline/steps/exceptions.py
azureml/contrib/automl/pipeline/steps/utilities.py
azureml/contrib/automl/pipeline/steps/_assets/__init__.py
azureml/contrib/automl/pipeline/steps/_assets/allocation_explanation_wrapper.py
azureml/contrib/automl/pipeline/steps/_assets/allocation_wrapper.py
azureml/contrib/automl/pipeline/steps/_assets/automl_forecast_wrapper.py
azureml/contrib/automl/pipeline/steps/_assets/automl_training_wrapper.py
azureml/contrib/automl/pipeline/steps/_assets/data_aggregation_and_validation_wrapper.py
azureml/contrib/automl/pipeline/steps/_assets/hierarchy_builder_wrapper.py
azureml/contrib/automl/pipeline/steps/_assets/many_models_inference_driver.py
azureml/contrib/automl/pipeline/steps/_assets/many_models_train_driver.py
azureml/contrib/automl/pipeline/steps/_assets/partition_inference_dataset_wrapper.py
azureml/contrib/automl/pipeline/steps/_assets/partition_training_dataset_wrapper.py
azureml/contrib/automl/pipeline/steps/_assets/proportions_calculation_wrapper.py
azureml_contrib_automl_pipeline_steps-1.60.0.dist-info/licenses/LICENSE.txt
azureml_contrib_automl_pipeline_steps-1.60.0.dist-info/METADATA
azureml_contrib_automl_pipeline_steps-1.60.0.dist-info/WHEEL
azureml_contrib_automl_pipeline_steps-1.60.0.dist-info/namespace_packages.txt
azureml_contrib_automl_pipeline_steps-1.60.0.dist-info/top_level.txt
azureml_contrib_automl_pipeline_steps-1.60.0.dist-info/RECORD
