Metadata-Version: 2.4
Name: azureml-contrib-automl-pipeline-steps
Version: 1.60.0
Summary: Helper classes, modules for creating AutoML many models train/inference steps using ParallelRunStep
Home-page: https://docs.microsoft.com/python/api/overview/azure/ml/?view=azure-ml-py
Author: Microsoft Corp
License: Proprietary https://aka.ms/azureml-preview-sdk-license 
Classifier: Intended Audience :: Developers
Classifier: Intended Audience :: Science/Research
Classifier: Programming Language :: Python :: 3.8
Classifier: Programming Language :: Python :: 3.9
Classifier: Programming Language :: Python :: 3.10
Classifier: Programming Language :: Python :: 3.11
Classifier: Topic :: Scientific/Engineering :: Artificial Intelligence
Requires-Python: >=3.8,<4.0
License-File: LICENSE.txt
Requires-Dist: azureml-pipeline-steps~=1.60.0
Dynamic: author
Dynamic: classifier
Dynamic: description
Dynamic: description-content-type
Dynamic: home-page
Dynamic: license
Dynamic: license-file
Dynamic: requires-dist
Dynamic: requires-python
Dynamic: summary
